odoo/addons/pos_no_cash_bank_statement/README.rst
odoo/addons/pos_no_cash_bank_statement/__init__.py
odoo/addons/pos_no_cash_bank_statement/__manifest__.py
odoo/addons/pos_no_cash_bank_statement/i18n/ar.po
odoo/addons/pos_no_cash_bank_statement/i18n/es.po
odoo/addons/pos_no_cash_bank_statement/i18n/it.po
odoo/addons/pos_no_cash_bank_statement/i18n/pos_no_cash_bank_statement.pot
odoo/addons/pos_no_cash_bank_statement/models/__init__.py
odoo/addons/pos_no_cash_bank_statement/models/pos_payment_method.py
odoo/addons/pos_no_cash_bank_statement/models/pos_session.py
odoo/addons/pos_no_cash_bank_statement/readme/CONTRIBUTORS.rst
odoo/addons/pos_no_cash_bank_statement/readme/DESCRIPTION.rst
odoo/addons/pos_no_cash_bank_statement/static/description/icon.png
odoo/addons/pos_no_cash_bank_statement/static/description/index.html
odoo/addons/pos_no_cash_bank_statement/views/pos_payment_method.xml
odoo14_addon_pos_no_cash_bank_statement-14.0.1.1.0.dist-info/METADATA
odoo14_addon_pos_no_cash_bank_statement-14.0.1.1.0.dist-info/WHEEL
odoo14_addon_pos_no_cash_bank_statement-14.0.1.1.0.dist-info/top_level.txt
odoo14_addon_pos_no_cash_bank_statement-14.0.1.1.0.dist-info/RECORD
